xambot/__init__.py
cryptoXam-0.0.111.0.dist-info/METADATA
cryptoXam-0.0.111.0.dist-info/WHEEL
cryptoXam-0.0.111.0.dist-info/top_level.txt
cryptoXam-0.0.111.0.dist-info/RECORD
