Metadata-Version: 2.1
Name: cryptoXam
Version: 0.0.111.0
Summary: A Data Science Package written in python.
Home-page: UNKNOWN
Author: Max Paul
Author-email: maxkpaul21@gmail.com
License: UNKNOWN
Platform: UNKNOWN
Classifier: Programming Language :: Python :: 3
Classifier: License :: OSI Approved :: MIT License
Classifier: Operating System :: OS Independent
Requires-Dist: ccxt
Requires-Dist: pandas
Requires-Dist: plotly
Requires-Dist: pycoingecko
Requires-Dist: twine
Requires-Dist: wheel
